nonebot_plugin_with_ai_agents/__init__.py
nonebot_plugin_with_ai_agents/handler.py
nonebot_plugin_with_ai_agents/llm/__init__.py
nonebot_plugin_with_ai_agents/llm/agents.py
nonebot_plugin_with_ai_agents/llm/central_brain.py
nonebot_plugin_with_ai_agents/llm/config.py
nonebot_plugin_with_ai_agents/llm/llms/__init__.py
nonebot_plugin_with_ai_agents/llm/llms/base.py
nonebot_plugin_with_ai_agents/llm/llms/dashscope.py
nonebot_plugin_with_ai_agents/llm/llms/glm.py
nonebot_plugin_with_ai_agents/llm/llms/openai.py
nonebot_plugin_with_ai_agents/llm/mem_stores.py
nonebot_plugin_with_ai_agents/llm/services.py
nonebot_plugin_with_ai_agents/llm/utils/__init__.py
nonebot_plugin_with_ai_agents/llm/utils/prompts.py
nonebot_plugin_with_ai_agents/llm/utils/retrievers.py
nonebot_plugin_with_ai_agents-0.1.15.dist-info/METADATA
nonebot_plugin_with_ai_agents-0.1.15.dist-info/WHEEL
nonebot_plugin_with_ai_agents-0.1.15.dist-info/RECORD
